{"problem_id": 13637, "annotation": "xiaokaizhang_2023-03-06", "source": "UniGeo-train-1628569789161", "problem_level": 1, "problem_text_cn": "", "problem_text_en": "Given PR≅PQ. S is the midpoint of QR . Complete the proof that △PQS≅△PRS . (Elements:  QS ,  RS ,  △PRS ,  △PQS ,  PS , )", "problem_img": "13637.png", "construction_cdl": ["Polygon()", "Collinear()", "Cocircular()"], "text_cdl": [], "image_cdl": [], "goal_cdl": "", "problem_answer": "", "theorem_seqs": [], "raw_statement": ["S is the midpoint of QR", "PR≅PQ", "QS≅RS", "PS≅PS", "△PQS≅△PRS"], "raw_reason": ["Given", "Given", "Definition of midpoint", "Reflexive Property of Congruence", "SSS"], "raw_proving_sequence": ["R_19", "E_0", "congruent", "E_1", "R_14", "E_4", "congruent", "E_4", "R_30", "E_3", "congruent", "E_2"]}