{"problem_id": 18594, "annotation": "xiaokaizhang_2023-03-06", "source": "UniGeo-train-1628661781993", "problem_level": 1, "problem_text_cn": "", "problem_text_en": "Given ∠Q≅∠U and ∠T≅∠R. Complete the proof that QS/UV=QT/RU. (Elements:  UV ,  △UVR ,  QT ,  QS ,  RU ,  △QST , )", "problem_img": "18594.png", "construction_cdl": ["Polygon()", "Collinear()", "Cocircular()"], "text_cdl": [], "image_cdl": [], "goal_cdl": "", "problem_answer": "", "theorem_seqs": [], "raw_statement": ["∠Q≅∠U", "∠T≅∠R", "△QST~△UVR", "QS/UV=QT/RU"], "raw_reason": ["Given", "Given", "AA Similarity", "Definition of similarity"], "raw_proving_sequence": ["R_21", "E_5", "similar", "E_1", "R_28", "E_3", "/", "E_0", "=", "E_2", "/", "E_4"]}