{"problem_id": 19657, "annotation": "xiaokaizhang_2023-03-06", "source": "UniGeo-val-1628647481340", "problem_level": 1, "problem_text_cn": "", "problem_text_en": "Given ∠T≅∠V. WX⟂TX and WX⟂VW . Complete the proof that △VWX≅△TXW . (Elements:  ∠VWX ,  △VWX ,  △TXW ,  WX ,  ∠TXW , )", "problem_img": "19657.png", "construction_cdl": ["Polygon()", "Collinear()", "Cocircular()"], "text_cdl": [], "image_cdl": [], "goal_cdl": "", "problem_answer": "", "theorem_seqs": [], "raw_statement": ["WX⟂TX", "∠T≅∠V", "WX⟂VW", "∠TXW≅∠VWX", "WX≅WX", "△VWX≅△TXW"], "raw_reason": ["Given", "Given", "Given", "All right angles are congruent", "Reflexive Property of Congruence", "AAS"], "raw_proving_sequence": ["R_3", "E_4", "congruent", "E_0", "R_14", "E_3", "congruent", "E_3", "R_0", "E_1", "congruent", "E_2"]}