{
  "problem_id": 11165,
  "annotation": "xiaokaizhang_2023-03-06",
  "source": "GeoQA-area-11569",
  "problem_level": 1,
  "problem_text_cn": "如图，在菱形ABCD中，∠ABC＝60°，AB＝4．若点E、F、G、H分别是边AB、BC、CD、DA的中点，连接EF、FG、GH、HE，则四边形EFGH的面积为（）",
  "problem_text_en": "",
  "problem_img": "11165.png",
  "construction_cdl": [
    "Shape()",
    "Collinear()",
    "Cocircular()"
  ],
  "text_cdl": [],
  "image_cdl": [
    "Equal(LengthOfLine(),1)",
    "Equal(MeasureOfAngle(),1)"
  ],
  "goal_cdl": "Value()",
  "problem_answer": "4√{3}",
  "theorem_seqs": [],
  "raw_answer": "连接AC、BD交于O，∵四边形ABCD是菱形，∴AC⊥BD，∵点E、F、G、H分别是边AB、BC、CD和DA的中点，∴EH∥BD，FG∥BD，EF∥AC，HG∥AC，∴EH∥FG，EF∥HG，∴四边形EFGH是平行四边形，∵AC⊥BD，∴∠AOB＝90°，∴∠BAO+∠ABO＝90°，∵∠AEH＝∠ABO，∠BEF＝∠EAO，∴∠AEO+∠BEF＝90°，∴∠HEF＝90°，∴四边形EFGH是矩形，∵在菱形ABCD中，∠ABC＝60°，∴△ABC是等边三角形，∴AC＝AB＝4，BD＝4√{3}，∴EF＝0.5×AC＝2，∴EH＝0.5×BD＝2√{3}，∴四边形EFGH的面积为2×2×√{3}＝4√{3}．故选：C．"
}