{
  "problem_id": 9664,
  "annotation": "xiaokaizhang_2023-03-06",
  "source": "GeoQA-angle-10068",
  "problem_level": 1,
  "problem_text_cn": "BP是∠ABC的平分线，CP是∠ACB的邻补角的平分线，∠ABP＝20°，∠ACP＝50°，则∠P＝（）",
  "problem_text_en": "",
  "problem_img": "9664.png",
  "construction_cdl": [
    "Shape()",
    "Collinear()",
    "Cocircular()"
  ],
  "text_cdl": [],
  "image_cdl": [
    "Equal(LengthOfLine(),1)",
    "Equal(MeasureOfAngle(),1)"
  ],
  "goal_cdl": "Value()",
  "problem_answer": "30°",
  "theorem_seqs": [],
  "raw_answer": "∵CP是∠ACM的角平分线，∠ACP＝90°，∴∠ACM＝2∠ACP＝100°，∴∠ACB＝80°，∵BP是∠ABC的角平分线，∠ABP＝20°，∴∠CBP＝∠ABP＝20°，∴∠P＝180°﹣∠CBP﹣∠ACB﹣∠ACP＝180°﹣20°﹣80°﹣50°＝30°．故选：A．"
}