{"problem_id": 1560, "annotation": "xiaokaizhang_2023-03-06", "source": "GeometryQA-1375", "problem_level": 1, "problem_text_cn": "有一个长方体容器，从里面量长5分米，宽4分米，高6分米，里面注有水，水深3分米，如果把一棱长2分米的正方体铁块完全浸没在水中，水面上升多少？", "problem_text_en": "", "problem_img": "1560.png", "construction_cdl": ["Polygon()", "Collinear()", "Cocircular()"], "text_cdl": [], "image_cdl": [], "goal_cdl": "", "problem_answer": "0.4", "theorem_seqs": [], "raw_equation": "x=cubic_volume(2)/rectangle_area(5, 4)", "raw_knowledge": ["(cubic, side * side * side = area)", "(rectangle, length * width = area)"]}