{"source": "Geometry3K-283", "id": 1867, "problem": "Find the area of the quadrilateral.", "choices": ["405", "499.5", "684.5", "999"], "answer": "B", "problem_type_graph": ["Triangle", "Other"], "text_logic_form": ["Find(AreaOf(Quadrilateral($)))"], "diagram_logic_form": ["Equals(LengthOf(Line(F,H)),37)", "Equals(LengthOf(Line(A,I)),18)", "Equals(LengthOf(Line(G,B)),9)", "PointLiesOnLine(A,Line(F,H))", "PointLiesOnLine(A,Line(F,B))", "PointLiesOnLine(B,Line(F,H))", "PointLiesOnLine(B,Line(A,H))", "Perpendicular(Line(I,A),Line(F,H))", "Perpendicular(Line(B,G),Line(F,H))", ""]}