{"source": "Geometry3K-2140", "id": 3724, "problem": "Q is the incenter of \\triangle J K L. Find Q P.", "choices": ["15", "20", "25", "30"], "answer": "A", "problem_type_graph": ["Triangle"], "text_logic_form": ["IsIncenterOf(Point(Q),Triangle(J,K,L))", "Find(LengthOf(Line(Q,P)))"], "diagram_logic_form": ["Equals(MeasureOf(Angle(P,L,Q)),26)", "Equals(LengthOf(Line(J,P)),20)", "Equals(MeasureOf(Angle(M,K,Q)),29)", "Equals(LengthOf(Line(J,Q)),25)", "PointLiesOnLine(N,Line(J,K))", "PointLiesOnLine(P,Line(J,L))", "PointLiesOnLine(M,Line(K,L))", "Perpendicular(Line(P,L),Line(P,Q))", "Perpendicular(Line(M,L),Line(Q,M))", "Perpendicular(Line(Q,N),Line(K,N))"]}