{"problem_id": 18216, "annotation": "xiaokaizhang_2023-03-06", "source": "UniGeo-train-1628600047994", "problem_level": 1, "problem_text_cn": "", "problem_text_en": "Given ∠H≅∠I and ∠E≅∠F. Complete the proof that EG/FJ=GH/IJ. (Elements:  △EGH ,  GH ,  △FJI ,  EG ,  IJ ,  FJ , )", "problem_img": "18216.png", "construction_cdl": ["Polygon()", "Collinear()", "Cocircular()"], "text_cdl": [], "image_cdl": [], "goal_cdl": "", "problem_answer": "", "theorem_seqs": [], "raw_statement": ["∠H≅∠I", "∠E≅∠F", "△EGH~△FJI", "EG/FJ=GH/IJ"], "raw_reason": ["Given", "Given", "AA Similarity", "Definition of similarity"], "raw_proving_sequence": ["R_21", "E_0", "similar", "E_2", "R_28", "E_3", "/", "E_5", "=", "E_1", "/", "E_4"]}