{
  "23750": {
    "problem_id": 23750,
    "added_cdl": [
      "Equation(ll_ac**2-ll_ad**2+2*ll_ad*ll_dc*cos(pi*ma_adc/180)-ll_dc**2)"
    ],
    "goal_cdl": "Value(LengthOfLine(AD))",
    "problem_answer": "18*cos(13*pi/45)",
    "theorem_seqs": [
      "cosine_theorem(1,ADC)"
    ],
    "theorem_seqs_dag": {
      "START": [
        "cosine_theorem(1,ADC)"
      ]
    }
  },
  "23751": {
    "problem_id": 23751,
    "added_cdl": [],
    "goal_cdl": "Value(LengthOfLine(AD))",
    "problem_answer": "18*cos(13*pi/45)",
    "theorem_seqs": [
      "cosine_theorem(1,DCA)",
      "cosine_theorem(1,ADC)"
    ],
    "theorem_seqs_dag": {
      "START": [
        "cosine_theorem(1,DCA)",
        "cosine_theorem(1,ADC)"
      ]
    }
  },
  "23752": {
    "problem_id": 23752,
    "added_cdl": [
      "Equation(ll_ac**2-ll_ad**2+2*ll_ad*ll_dc*cos(pi*ma_adc/180)-ll_dc**2)"
    ],
    "goal_cdl": "Value(x)",
    "problem_answer": "18*cos(13*pi/45)",
    "theorem_seqs": [
      "cosine_theorem(1,ADC)"
    ],
    "theorem_seqs_dag": {
      "START": [
        "cosine_theorem(1,ADC)"
      ]
    }
  },
  "23753": {
    "problem_id": 23753,
    "added_cdl": [],
    "goal_cdl": "Value(x)",
    "problem_answer": "18*cos(13*pi/45)",
    "theorem_seqs": [
      "cosine_theorem(1,DCA)",
      "cosine_theorem(1,ADC)"
    ],
    "theorem_seqs_dag": {
      "START": [
        "cosine_theorem(1,DCA)",
        "cosine_theorem(1,ADC)"
      ]
    }
  },
  "23754": {
    "problem_id": 23754,
    "added_cdl": [
      "Equation(ll_ac**2-ll_ad**2+2*ll_ad*ll_dc*cos(pi*ma_adc/180)-ll_dc**2)"
    ],
    "goal_cdl": "Value(LengthOfLine(DC))",
    "problem_answer": "18*cos(19*pi/90)",
    "theorem_seqs": [
      "cosine_theorem(1,ADC)"
    ],
    "theorem_seqs_dag": {
      "START": [
        "cosine_theorem(1,ADC)"
      ]
    }
  },
  "23755": {
    "problem_id": 23755,
    "added_cdl": [],
    "goal_cdl": "Value(LengthOfLine(DC))",
    "problem_answer": "18*cos(19*pi/90)",
    "theorem_seqs": [
      "cosine_theorem(1,DCA)",
      "cosine_theorem(1,ADC)"
    ],
    "theorem_seqs_dag": {
      "START": [
        "cosine_theorem(1,DCA)",
        "cosine_theorem(1,ADC)"
      ]
    }
  }
}