{
  "32367": {
    "problem_id": 32367,
    "added_cdl": [
      "Equation(ma_abc+ma_bda+ma_dab-180)"
    ],
    "goal_cdl": "Value(MeasureOfAngle(DAB))",
    "problem_answer": "58",
    "theorem_seqs": [
      "adjacent_complementary_angle(1,BDA,ADC)"
    ],
    "theorem_seqs_dag": {
      "START": [
        "adjacent_complementary_angle(1,BDA,ADC)"
      ]
    }
  },
  "32368": {
    "problem_id": 32368,
    "added_cdl": [],
    "goal_cdl": "Value(MeasureOfAngle(DAB))",
    "problem_answer": "58",
    "theorem_seqs": [
      "triangle_property_angle_sum(1,ABD)",
      "adjacent_complementary_angle(1,BDA,ADC)"
    ],
    "theorem_seqs_dag": {
      "START": [
        "triangle_property_angle_sum(1,ABD)",
        "adjacent_complementary_angle(1,BDA,ADC)"
      ]
    }
  },
  "32369": {
    "problem_id": 32369,
    "added_cdl": [
      "Equation(ma_abc+ma_bda+ma_dab-180)"
    ],
    "goal_cdl": "Value(x)",
    "problem_answer": "58",
    "theorem_seqs": [
      "adjacent_complementary_angle(1,BDA,ADC)"
    ],
    "theorem_seqs_dag": {
      "START": [
        "adjacent_complementary_angle(1,BDA,ADC)"
      ]
    }
  },
  "32370": {
    "problem_id": 32370,
    "added_cdl": [],
    "goal_cdl": "Value(x)",
    "problem_answer": "58",
    "theorem_seqs": [
      "triangle_property_angle_sum(1,ABD)",
      "adjacent_complementary_angle(1,BDA,ADC)"
    ],
    "theorem_seqs_dag": {
      "START": [
        "triangle_property_angle_sum(1,ABD)",
        "adjacent_complementary_angle(1,BDA,ADC)"
      ]
    }
  },
  "32371": {
    "problem_id": 32371,
    "added_cdl": [],
    "goal_cdl": "Value(MeasureOfAngle(BDA))",
    "problem_answer": "80",
    "theorem_seqs": [
      "adjacent_complementary_angle(1,BDA,ADC)"
    ],
    "theorem_seqs_dag": {
      "START": [
        "adjacent_complementary_angle(1,BDA,ADC)"
      ]
    }
  }
}