{
  "127574": {
    "problem_id": 127574,
    "added_cdl": [],
    "goal_cdl": "Equal(MeasureOfArc(OAC),MeasureOfAngle(MOA))",
    "problem_answer": "0",
    "theorem_seqs": [
      "arc_property_center_angle(1,OAC,O)"
    ],
    "theorem_seqs_dag": {
      "START": [
        "arc_property_center_angle(1,OAC,O)"
      ]
    }
  },
  "127575": {
    "problem_id": 127575,
    "added_cdl": [
      "Equal(MeasureOfArc(OAC),MeasureOfAngle(MOA))"
    ],
    "goal_cdl": "Value(MeasureOfAngle(MOA))",
    "problem_answer": "110",
    "theorem_seqs": [
      "arc_property_circumference_angle_external(1,OAC,B)"
    ],
    "theorem_seqs_dag": {
      "START": [
        "arc_property_circumference_angle_external(1,OAC,B)"
      ]
    }
  },
  "127576": {
    "problem_id": 127576,
    "added_cdl": [],
    "goal_cdl": "Value(MeasureOfAngle(MOA))",
    "problem_answer": "110",
    "theorem_seqs": [
      "arc_property_center_angle(1,OAC,O)",
      "arc_property_circumference_angle_external(1,OAC,B)"
    ],
    "theorem_seqs_dag": {
      "START": [
        "arc_property_center_angle(1,OAC,O)",
        "arc_property_circumference_angle_external(1,OAC,B)"
      ]
    }
  },
  "127577": {
    "problem_id": 127577,
    "added_cdl": [],
    "goal_cdl": "Value(MeasureOfArc(OAC))",
    "problem_answer": "110",
    "theorem_seqs": [
      "arc_property_circumference_angle_external(1,OAC,B)"
    ],
    "theorem_seqs_dag": {
      "START": [
        "arc_property_circumference_angle_external(1,OAC,B)"
      ]
    }
  }
}