{
  "131571": {
    "problem_id": 131571,
    "added_cdl": [],
    "goal_cdl": "Equal(MeasureOfArc(OAC),MeasureOfAngle(COA))",
    "problem_answer": "0",
    "theorem_seqs": [
      "arc_property_center_angle(1,OAC,O)"
    ],
    "theorem_seqs_dag": {
      "START": [
        "arc_property_center_angle(1,OAC,O)"
      ]
    }
  },
  "131572": {
    "problem_id": 131572,
    "added_cdl": [
      "Equal(MeasureOfAngle(CED),180)",
      "Equation(-ma_aed-ma_cea+ma_ced)",
      "Equation(ma_cda-mar_oac/2)",
      "Equation(ma_aed+ma_cda+ma_dab-180)"
    ],
    "goal_cdl": "Value(MeasureOfAngle(DAO))",
    "problem_answer": "19",
    "theorem_seqs": [
      "arc_property_center_angle(1,OAC,O)"
    ],
    "theorem_seqs_dag": {
      "START": [
        "arc_property_center_angle(1,OAC,O)"
      ]
    }
  },
  "131573": {
    "problem_id": 131573,
    "added_cdl": [
      "Equation(-ma_aed-ma_cea+ma_ced)",
      "Equation(ma_cda-mar_oac/2)",
      "Equation(ma_aed+ma_cda+ma_dab-180)"
    ],
    "goal_cdl": "Value(MeasureOfAngle(DAO))",
    "problem_answer": "19",
    "theorem_seqs": [
      "flat_angle(1,CED)",
      "arc_property_center_angle(1,OAC,O)"
    ],
    "theorem_seqs_dag": {
      "START": [
        "flat_angle(1,CED)",
        "arc_property_center_angle(1,OAC,O)"
      ]
    }
  },
  "131574": {
    "problem_id": 131574,
    "added_cdl": [
      "Equation(ma_cda-mar_oac/2)",
      "Equation(ma_aed+ma_cda+ma_dab-180)"
    ],
    "goal_cdl": "Value(MeasureOfAngle(DAO))",
    "problem_answer": "19",
    "theorem_seqs": [
      "angle_addition(1,CEA,AED)",
      "flat_angle(1,CED)",
      "arc_property_center_angle(1,OAC,O)"
    ],
    "theorem_seqs_dag": {
      "START": [
        "angle_addition(1,CEA,AED)",
        "flat_angle(1,CED)",
        "arc_property_center_angle(1,OAC,O)"
      ]
    }
  },
  "131575": {
    "problem_id": 131575,
    "added_cdl": [
      "Equation(ma_aed+ma_cda+ma_dab-180)"
    ],
    "goal_cdl": "Value(MeasureOfAngle(DAO))",
    "problem_answer": "19",
    "theorem_seqs": [
      "arc_property_circumference_angle_external(1,OAC,D)",
      "angle_addition(1,CEA,AED)",
      "flat_angle(1,CED)",
      "arc_property_center_angle(1,OAC,O)"
    ],
    "theorem_seqs_dag": {
      "START": [
        "arc_property_circumference_angle_external(1,OAC,D)",
        "angle_addition(1,CEA,AED)",
        "flat_angle(1,CED)",
        "arc_property_center_angle(1,OAC,O)"
      ]
    }
  },
  "131576": {
    "problem_id": 131576,
    "added_cdl": [],
    "goal_cdl": "Value(MeasureOfAngle(DAO))",
    "problem_answer": "19",
    "theorem_seqs": [
      "triangle_property_angle_sum(1,DAE)",
      "arc_property_circumference_angle_external(1,OAC,D)",
      "angle_addition(1,CEA,AED)",
      "flat_angle(1,CED)",
      "arc_property_center_angle(1,OAC,O)"
    ],
    "theorem_seqs_dag": {
      "START": [
        "triangle_property_angle_sum(1,DAE)",
        "arc_property_circumference_angle_external(1,OAC,D)",
        "angle_addition(1,CEA,AED)",
        "flat_angle(1,CED)",
        "arc_property_center_angle(1,OAC,O)"
      ]
    }
  },
  "131577": {
    "problem_id": 131577,
    "added_cdl": [],
    "goal_cdl": "Value(MeasureOfArc(OAC))",
    "problem_answer": "90",
    "theorem_seqs": [
      "arc_property_center_angle(1,OAC,O)"
    ],
    "theorem_seqs_dag": {
      "START": [
        "arc_property_center_angle(1,OAC,O)"
      ]
    }
  },
  "131578": {
    "problem_id": 131578,
    "added_cdl": [
      "Equation(ma_cda-mar_oac/2)"
    ],
    "goal_cdl": "Value(MeasureOfAngle(EDA))",
    "problem_answer": "45",
    "theorem_seqs": [
      "arc_property_center_angle(1,OAC,O)"
    ],
    "theorem_seqs_dag": {
      "START": [
        "arc_property_center_angle(1,OAC,O)"
      ]
    }
  },
  "131579": {
    "problem_id": 131579,
    "added_cdl": [],
    "goal_cdl": "Value(MeasureOfAngle(EDA))",
    "problem_answer": "45",
    "theorem_seqs": [
      "arc_property_circumference_angle_external(1,OAC,D)",
      "arc_property_center_angle(1,OAC,O)"
    ],
    "theorem_seqs_dag": {
      "START": [
        "arc_property_circumference_angle_external(1,OAC,D)",
        "arc_property_center_angle(1,OAC,O)"
      ]
    }
  },
  "131580": {
    "problem_id": 131580,
    "added_cdl": [
      "Equation(-ma_aed-ma_cea+ma_ced)"
    ],
    "goal_cdl": "Value(MeasureOfAngle(AED))",
    "problem_answer": "116",
    "theorem_seqs": [
      "flat_angle(1,CED)"
    ],
    "theorem_seqs_dag": {
      "START": [
        "flat_angle(1,CED)"
      ]
    }
  },
  "131581": {
    "problem_id": 131581,
    "added_cdl": [],
    "goal_cdl": "Value(MeasureOfAngle(AED))",
    "problem_answer": "116",
    "theorem_seqs": [
      "angle_addition(1,CEA,AED)",
      "flat_angle(1,CED)"
    ],
    "theorem_seqs_dag": {
      "START": [
        "angle_addition(1,CEA,AED)",
        "flat_angle(1,CED)"
      ]
    }
  },
  "131582": {
    "problem_id": 131582,
    "added_cdl": [],
    "goal_cdl": "Value(MeasureOfAngle(CED))",
    "problem_answer": "180",
    "theorem_seqs": [
      "flat_angle(1,CED)"
    ],
    "theorem_seqs_dag": {
      "START": []
    }
  }
}