{
  "problem_id": 7210,
  "annotation": "xiaokaizhang_2023-03-06",
  "source": "GeoQA-4403",
  "problem_level": 1,
  "problem_text_cn": "如图,直线BC与⊙O相切于点A,AD是⊙O的弦,连接OD,若∠DAC=50°,则∠ODA的度数为()",
  "problem_text_en": "As shown in the figure, the straight line BC is tangent to ⊙O at point A, AD is the chord of ⊙O. Connect OD, if ∠DAC = N_0, then the degree of ∠ODA is ()",
  "problem_img": "7210.png",
  "construction_cdl": [
    "Shape()",
    "Collinear()",
    "Cocircular()"
  ],
  "text_cdl": [
    "Equal(LengthOfLine(),1)",
    "Equal(MeasureOfAngle(),1)"
  ],
  "image_cdl": [],
  "goal_cdl": "Value(MeasureOfAngle())",
  "problem_answer": "40",
  "theorem_seqs": [],
  "raw_answer": "解:∵直线BC与⊙O相切于点A,∴OA⊥BC,∴∠OAC=90°,∵∠DAC=50°,∴∠OAD=40°,∵OD=OA,∴∠ODA=∠OAD=40°,故选:B．"
}