{"problem_id": 6433, "annotation": "xiaokaizhang_2023-03-06", "source": "GeoQA-3099", "problem_level": 1, "problem_text_cn": "如图,AB是⊙O的直径,CD是⊙O的弦,连结AC、AD、BD,若∠CAB=35°,则∠ADC的度数为()", "problem_text_en": "As shown in the figure, AB is the diameter of ⊙O, CD is the chord of ⊙O, connect AC, AD, BD, if ∠CAB = N_0, then the degree of ∠ADC is ()", "problem_img": "6433.png", "construction_cdl": ["Polygon()", "Collinear()", "Cocircular()"], "text_cdl": [], "image_cdl": [], "goal_cdl": "", "problem_answer": "", "theorem_seqs": [], "raw_choices": ["35°", "55°", "65°", "70°"], "raw_answer": "解:∵AB是⊙O的直径,∴∠ADB=90°,又∵∠CDB=∠CAB=35°(圆周角定理),∴∠ADC=90°-35°=55°．故选:B．", "raw_label": 1, "raw_formal_point": ["圆周角"], "raw_comment": "本题考查了圆周角定理的知识,解答本题的关键是掌握圆周角定理的内容．"}