{"problem_id": 7882, "annotation": "xiaokaizhang_2023-03-06", "source": "GeoQA-5713", "problem_level": 1, "problem_text_cn": "如图,已知▱ABCD的四个内角的平分线分别相交于点E、F、G、H,连接AC．若EF=2,FG=GC=5,则AC的长是()", "problem_text_en": "As shown in the figure, it is known that the bisectors of the four inner corners of ▱ABCD intersect at points E, F, G, and H respectively. Connect AC. If EF = N_0, FG = GC = N_1, then the length of AC is ()", "problem_img": "7882.png", "construction_cdl": ["Polygon()", "Collinear()", "Cocircular()"], "text_cdl": [], "image_cdl": [], "goal_cdl": "", "problem_answer": "", "theorem_seqs": [], "raw_choices": ["12", "13", "6√{5}", "8√{3}"], "raw_answer": "解:如图,作AP⊥CH交CH的延长线与P．∵四边形ABCD是平行四边形,▱ABCD的四个内角的平分线分别相交于点E、F、G、H,∴易证四边形EFGH是矩形,四边形AEHP是矩形,△ABE≌△CDG,可得PA=FG=5,AE=PH=CG=5,CP=CG+PH+GH=2+10=12,在Rt△APC中,AC=∠\\beta=∠ZZN=√{PA^{2}+PC^{2}}=13．故选:B．", "raw_label": 1, "raw_formal_point": ["勾股定理", "矩形", "平行线", "平行四边形", "平行线分线段成比例"], "raw_comment": "本题考查平行四边形的性质、矩形的判定和性质、全等三角形的判定和性质、勾股定理、平行线分线段成比例定理等知识,本题的综合性比较强,解题的关键是灵活运用所学知识解决问题,学会利用参数,构建方程解决问题,属于中考选择题中的压轴题"}